{"createdDate":"2019-10-19 21:50:13","id":"0F1FCA7E-A7A1-4A37-B46B-EE94A8AF87C2","modifiedDate":"2019-10-19 21:50:13","title":"training-data","dataResult":{"itemsCount":320,"dataURL":"file:\/\/\/Users\/nickarner\/Downloads\/Environmental-Sound-Classification-ESC-using-neural-networks-and-other-classifiers-master\/training-data\/","classesCount":10,"analysis":{"summary":{"canUseValidation":1,"classCount":10,"sampleCount":320},"issues":[{"description":"10 classes found, including 006-Person sneeze, 004-Baby cry, 007-Helicopter","severity":"info"},{"description":"320 sounds found, automatically creating validation set","severity":"good"},{"description":"Smallest class is \"002-Rain\" with 32 sounds","severity":"warning"},{"description":"Largest class is \"006-Person sneeze\" with 32 sounds","severity":"info"}],"classifierAnalysis":{"columns":[],"vizualizerSpec":"","labelStats":{"006-Person sneeze":32,"004-Baby cry":32,"010-Fire crackling":32,"005-Clock tick":32,"009-Rooster":32,"002-Rain":32,"001-Dog bark":32,"007-Helicopter":32,"008-Chainsaw":32,"003-Sea waves":32}}}},"preferredFilename":"training-data","version":"1.0","pathType":0,"experimentIDs":["FCEE9F0F-C884-4BA7-9C5A-190FC5741904"]}